best/__init__.py
best/integration/__init__.py
best/unit/__init__.py
best/unit/conftest.py
best/unit/test_glue_session.py
best/unit/test_glue_session_demo.py
best/unit/test_session_apis.py
app_store_server_library-19.4.6.dist-info/LICENSE.txt
app_store_server_library-19.4.6.dist-info/METADATA
app_store_server_library-19.4.6.dist-info/WHEEL
app_store_server_library-19.4.6.dist-info/top_level.txt
app_store_server_library-19.4.6.dist-info/RECORD
